dftinputgen/VERSION.txt
dftinputgen/__init__.py
dftinputgen/base.py
dftinputgen/cli.py
dftinputgen/utils.py
dftinputgen/data/__init__.py
dftinputgen/data/standard_atomic_weights.json
dftinputgen/demo/__init__.py
dftinputgen/demo/pwx.py
dftinputgen/qe/__init__.py
dftinputgen/qe/pwx.py
dftinputgen/qe/settings/__init__.py
dftinputgen/qe/settings/tags_and_groups.json
dftinputgen/qe/settings/calculation_presets/__init__.py
dftinputgen/qe/settings/calculation_presets/relax.json
dftinputgen/qe/settings/calculation_presets/scf.json
dftinputgen/qe/settings/calculation_presets/vc-relax.json
dftinputgen-0.1.2.dist-info/LICENSE
dftinputgen-0.1.2.dist-info/METADATA
dftinputgen-0.1.2.dist-info/WHEEL
dftinputgen-0.1.2.dist-info/entry_points.txt
dftinputgen-0.1.2.dist-info/top_level.txt
dftinputgen-0.1.2.dist-info/RECORD
