Metadata-Version: 2.1
Name: dftinputgen
Version: 0.1.2
Summary: Unopinionated library to generate input files for DFT codes
Home-page: https://github.com/CitrineInformatics/dft-input-gen
Author: Vinay Hegde
Author-email: vhegde@citrine.io
License: UNKNOWN
Platform: UNKNOWN
Classifier: Programming Language :: Python :: 2.7
Classifier: Programming Language :: Python :: 3.8
Requires-Dist: six
Requires-Dist: numpy
Requires-Dist: ase (<=3.17)
